random_number_provider/__init__.py
random_number_provider/_version.py
random_number_provider/app.py
random_number_provider/wsgi.py
random_number_provider/xsd/random_numbers_request.xsd
random_number_provider-0.1.6.dist-info/METADATA
random_number_provider-0.1.6.dist-info/WHEEL
random_number_provider-0.1.6.dist-info/entry_points.txt
random_number_provider-0.1.6.dist-info/top_level.txt
random_number_provider-0.1.6.dist-info/RECORD
