Metadata-Version: 2.1
Name: random_number_provider
Version: 0.1.6
Summary: Random numbers as a service
Home-page: https://github.com/twyleg/
Author: Torsten Wylegala
Author-email: mail@twyleg.de
License: GPL 3.0
Keywords: random numbers as a service
Requires-Dist: xmlschema ~=2.3.1
Requires-Dist: multimethod ~=1.10
Requires-Dist: gunicorn ~=21.2.0
Requires-Dist: flask ~=2.3.3
Requires-Dist: werkzeug ~=2.3.7
